bmpm/__init__.py
bmpm/__main__.py
BMPM-1.4.1.dist-info/LICENSE
BMPM-1.4.1.dist-info/METADATA
BMPM-1.4.1.dist-info/WHEEL
BMPM-1.4.1.dist-info/entry_points.txt
BMPM-1.4.1.dist-info/top_level.txt
BMPM-1.4.1.dist-info/RECORD
