Metadata-Version: 2.1
Name: BMPM
Version: 1.4.1
Summary: A program for bulk replacement of BYML map file parameters.
Home-page: https://github.com/SDarkMagic/BMPM
Author: SDarkMagic
Author-email: TheSDarkMagic@gmail.com
License: UNKNOWN
Platform: UNKNOWN
Classifier: Programming Language :: Python :: 3
Classifier: License :: OSI Approved :: MIT License
Classifier: Operating System :: OS Independent
Requires-Python: >=3.7
Requires-Dist: oead (>=1.1.1)
